django_smartbase_admin/__init__.py
django_smartbase_admin/actions/__init__.py
django_smartbase_admin/actions/admin_action_list.py
django_smartbase_admin/actions/advanced_filters.py
django_smartbase_admin/admin/__init__.py
django_smartbase_admin/admin/admin_base.py
django_smartbase_admin/admin/site.py
django_smartbase_admin/admin/widgets.py
django_smartbase_admin/apps.py
django_smartbase_admin/compilemessages.py
django_smartbase_admin/engine/__init__.py
django_smartbase_admin/engine/actions.py
django_smartbase_admin/engine/admin_base_view.py
django_smartbase_admin/engine/admin_entrypoint_view.py
django_smartbase_admin/engine/admin_view.py
django_smartbase_admin/engine/configuration.py
django_smartbase_admin/engine/const.py
django_smartbase_admin/engine/dashboard.py
django_smartbase_admin/engine/fake_inline.py
django_smartbase_admin/engine/field.py
django_smartbase_admin/engine/field_formatter.py
django_smartbase_admin/engine/filter_widgets.py
django_smartbase_admin/engine/global_filter_form.py
django_smartbase_admin/engine/menu_item.py
django_smartbase_admin/engine/modal_view.py
django_smartbase_admin/engine/request.py
django_smartbase_admin/integration/__init__.py
django_smartbase_admin/integration/django_cms.py
django_smartbase_admin/locale/sk/LC_MESSAGES/django.mo
django_smartbase_admin/locale/sk/LC_MESSAGES/django.po
django_smartbase_admin/makemessages.py
django_smartbase_admin/migrations/0001_initial.py
django_smartbase_admin/migrations/0002_auto_20230402_2316.py
django_smartbase_admin/migrations/0003_auto_20230402_2328.py
django_smartbase_admin/migrations/0004_alter_sbadminlistviewconfiguration_action_and_more.py
django_smartbase_admin/migrations/0005_sbadminuserconfiguration.py
django_smartbase_admin/migrations/0006_alter_sbadminuserconfiguration_color_scheme.py
django_smartbase_admin/migrations/__init__.py
django_smartbase_admin/models.py
django_smartbase_admin/monkeypatch/admin_readonly_field_monkeypatch.py
django_smartbase_admin-1.0.38.dist-info/LICENSE.md
django_smartbase_admin-1.0.38.dist-info/METADATA
django_smartbase_admin-1.0.38.dist-info/WHEEL
django_smartbase_admin-1.0.38.dist-info/RECORD
