Metadata-Version: 2.1
Name: django-smartbase-admin
Version: 1.0.38
Summary: 
Home-page: https://smartbase-sk.github.io/django-smartbase-admin-docs/
License: MIT
Author: SmartBase
Author-email: info@smartbase.sk
Requires-Python: >=3.10,<4.0
Classifier: Development Status :: 5 - Production/Stable
Classifier: Environment :: Web Environment
Classifier: Framework :: Django
Classifier: Intended Audience :: Developers
Classifier: License :: OSI Approved :: MIT License
Classifier: Operating System :: OS Independent
Classifier: Programming Language :: Python :: 3
Classifier: Programming Language :: Python :: 3.10
Classifier: Programming Language :: Python :: 3.11
Classifier: Programming Language :: Python :: 3.12
Classifier: Programming Language :: Python :: 3.13
Requires-Dist: django (>=4.1,<6.0)
Requires-Dist: django-admin-inline-paginator (>=0.4.0,<0.5.0)
Requires-Dist: django-ckeditor (>=6.7.1,<7.0.0)
Requires-Dist: django-filer (>=3.1.1,<4.0.0)
Requires-Dist: django-htmx (>=1.17.3,<2.0.0)
Requires-Dist: django-nested-admin (>=4.1.1,<5.0.0)
Requires-Dist: django-widget-tweaks (>=1.5.0,<2.0.0)
Requires-Dist: easy-thumbnails[svg] (>=2.8.5,<3.0.0)
Requires-Dist: setuptools (>=67.0.0,<68.0.0)
Requires-Dist: xlsxwriter (>=3.2.0,<4.0.0)
Project-URL: Repository, https://github.com/SmartBase-SK/django-smartbase-admin
